{
  "id": 11302671,
  "name": "Adamancipator Analyzer",
  "type": "Tuner Monster",
  "description": "If only your opponent controls a monster: You can Special Summon this card from your hand. During your Main Phase: You can excavate the top 5 cards of your Deck, and if you do, you can Special Summon 1 excavated Level 4 or lower non-Tuner Rock monster, also place the rest on the bottom of your Deck in any order. You can only use each effect of \"Adamancipator Analyzer\" once per turn.",
  "attack": 1500,
  "defense": 700,
  "level": 4,
  "attribute": "EARTH",
  "race": "Rock",
  "images": {
    "artwork_url": "https://images.ygoprodeck.com/images/cards/11302671.jpg",
    "small_url": "https://images.ygoprodeck.com/images/cards_small/11302671.jpg",
    "cropped_url": "https://images.ygoprodeck.com/images/cards_cropped/11302671.jpg"
  }
}
