{
  "id": 64977888,
  "name": "Apprentice Piper",
  "type": "Flip Effect Monster",
  "description": "FLIP: You can Special Summon 1 monster from your hand.\r\nIf this card is destroyed by battle or card effect and sent to the Graveyard: You can Special Summon 1 monster from your hand.",
  "attack": 100,
  "defense": 1500,
  "level": 2,
  "attribute": "DARK",
  "race": "Spellcaster",
  "images": {
    "artwork_url": "https://images.ygoprodeck.com/images/cards/64977888.jpg",
    "small_url": "https://images.ygoprodeck.com/images/cards_small/64977888.jpg",
    "cropped_url": "https://images.ygoprodeck.com/images/cards_cropped/64977888.jpg"
  }
}
