{
  "id": 61245672,
  "name": "Decode Talker Heatsoul",
  "type": "Link Monster",
  "description": "2+ Cyberse monsters with different Attributes\r\nGains 500 ATK for each monster it points to. (Quick Effect): You can pay 1000 LP; draw 1 card, then if your LP are 2000 or less, you can banish this card from the field, and if you do, Special Summon 1 Link-3 or lower Cyberse monster from your Extra Deck, except \"Decode Talker Heatsoul\". You can only use this effect of \"Decode Talker Heatsoul\" once per turn.",
  "attack": 2300,
  "defense": null,
  "level": null,
  "attribute": "FIRE",
  "race": "Cyberse",
  "images": {
    "artwork_url": "https://images.ygoprodeck.com/images/cards/61245672.jpg",
    "small_url": "https://images.ygoprodeck.com/images/cards_small/61245672.jpg",
    "cropped_url": "https://images.ygoprodeck.com/images/cards_cropped/61245672.jpg"
  }
}
