{
  "id": 37414347,
  "name": "F.A. Shining Star GT",
  "type": "Link Monster",
  "description": "2 Machine monsters\r\nGains ATK equal to the total Levels of the \"F.A.\" monsters this card points to x 300. Neither player takes any battle damage from attacks involving this card. Each time a \"F.A.\" Spell/Trap Card or effect is activated: Place 1 Athlete Counter on this card. When your opponent activates a monster effect (Quick Effect): You can remove 1 Athlete Counter from this card; negate the activation, and if you do, destroy it. You can only use this effect of \"F.A. Shining Star GT\" once per turn.",
  "attack": 0,
  "defense": null,
  "level": null,
  "attribute": "LIGHT",
  "race": "Machine",
  "images": {
    "artwork_url": "https://images.ygoprodeck.com/images/cards/37414347.jpg",
    "small_url": "https://images.ygoprodeck.com/images/cards_small/37414347.jpg",
    "cropped_url": "https://images.ygoprodeck.com/images/cards_cropped/37414347.jpg"
  }
}
