{
  "id": 77642288,
  "name": "Gladiator Beast Secutor",
  "type": "Effect Monster",
  "description": "If this card was Special Summoned by the effect of a \"Gladiator Beast\" monster, then at the end of any Battle Phase in which this card attacked or was attacked: Special Summon 2 \"Gladiator Beast\" monsters from your Deck, except \"Gladiator Beast Secutor\".",
  "attack": 400,
  "defense": 300,
  "level": 4,
  "attribute": "WIND",
  "race": "Reptile",
  "images": {
    "artwork_url": "https://images.ygoprodeck.com/images/cards/77642288.jpg",
    "small_url": "https://images.ygoprodeck.com/images/cards_small/77642288.jpg",
    "cropped_url": "https://images.ygoprodeck.com/images/cards_cropped/77642288.jpg"
  }
}
