{
  "id": 35307484,
  "name": "Malicevorous Spoon",
  "type": "Effect Monster",
  "description": "When a \"Malicevorous\" monster with a different name is Normal or Special Summoned to your side of the field (except during the Damage Step): You can target 1 Level 2 Fiend-Type monster in your Graveyard; Special Summon that target. Its effects are negated. You can only use the effect of \"Malicevorous Spoon\" once per turn.",
  "attack": 100,
  "defense": 500,
  "level": 2,
  "attribute": "DARK",
  "race": "Fiend",
  "images": {
    "artwork_url": "https://images.ygoprodeck.com/images/cards/35307484.jpg",
    "small_url": "https://images.ygoprodeck.com/images/cards_small/35307484.jpg",
    "cropped_url": "https://images.ygoprodeck.com/images/cards_cropped/35307484.jpg"
  }
}
