{
  "id": 15800838,
  "name": "Mind Crush",
  "type": "Trap Card",
  "description": "Declare 1 card name; if that card is in your opponent's hand, they must discard all copies of it, otherwise you discard 1 random card.",
  "race": "Normal",
  "images": {
    "artwork_url": "https://images.ygoprodeck.com/images/cards/15800838.jpg",
    "small_url": "https://images.ygoprodeck.com/images/cards_small/15800838.jpg",
    "cropped_url": "https://images.ygoprodeck.com/images/cards_cropped/15800838.jpg"
  }
}
