{
  "id": 36010310,
  "name": "Nunu, the Ogdoadic Remnant",
  "type": "Effect Monster",
  "description": "You can send this card from your hand to the GY; send 1 DARK Reptile monster from your Deck to the GY. If you control no monsters, or you control an \"Ogdoadic\" monster: You can Special Summon this card from your GY, but banish it when it leaves the field, also you cannot Special Summon monsters, except Reptile monsters, while this card is face-up in the Monster Zone. You can only use each effect of \"Nunu, the Ogdoadic Remnant\" once per turn.",
  "attack": 0,
  "defense": 0,
  "level": 4,
  "attribute": "LIGHT",
  "race": "Reptile",
  "images": {
    "artwork_url": "https://images.ygoprodeck.com/images/cards/36010310.jpg",
    "small_url": "https://images.ygoprodeck.com/images/cards_small/36010310.jpg",
    "cropped_url": "https://images.ygoprodeck.com/images/cards_cropped/36010310.jpg"
  }
}
