{
  "id": 13760677,
  "name": "P.M. Captor",
  "type": "Pendulum Effect Monster",
  "description": "[ Pendulum Effect ] \nWhen you Pendulum Summon a Zombie-Type monster(s): You can activate this effect; it cannot be destroyed by battle or card effects this turn.\n\n[ Monster Effect ] \nIf this card destroys a monster by battle: You can target 1 Pendulum Monster in your Graveyard; add it to your hand.",
  "attack": 1800,
  "defense": 0,
  "level": 4,
  "attribute": "DARK",
  "race": "Zombie",
  "images": {
    "artwork_url": "https://images.ygoprodeck.com/images/cards/13760677.jpg",
    "small_url": "https://images.ygoprodeck.com/images/cards_small/13760677.jpg",
    "cropped_url": "https://images.ygoprodeck.com/images/cards_cropped/13760677.jpg"
  }
}
