{
  "id": 73398797,
  "name": "Paladin of White Dragon",
  "type": "Ritual Effect Monster",
  "description": "You can Ritual Summon this card with \"White Dragon Ritual\". At the start of the Damage Step, if this card attacks a face-down Defense Position monster: Destroy that face-down monster. You can Tribute this card; Special Summon 1 \"Blue-Eyes White Dragon\" from your hand or Deck, but \"Blue-Eyes White Dragons\" cannot attack for the rest of this turn.",
  "attack": 1900,
  "defense": 1200,
  "level": 4,
  "attribute": "LIGHT",
  "race": "Dragon",
  "images": {
    "artwork_url": "https://images.ygoprodeck.com/images/cards/73398797.jpg",
    "small_url": "https://images.ygoprodeck.com/images/cards_small/73398797.jpg",
    "cropped_url": "https://images.ygoprodeck.com/images/cards_cropped/73398797.jpg"
  }
}
