{
  "id": 49858495,
  "name": "Power Pro Lady Sisters",
  "type": "Normal Monster",
  "description": "''The three Power Pro girls are best friends! And their passion for baseball soars like a home run!\r\nAoi Hayakawa was the first female player in the league. Her signature pitch is a submariner she calls The Marine Ball!\r\nMizuki Tachibana is more of a tomboy than her senpai, best known for her Crescent Moon Pitch and her love for the pudding sold down at Pawado!\r\nHijiri Rokudo is a catcher with a rare gift for baseball! She's been best friends with Mizuki since junior high and her favorite at Pawado is the Kintsuba!''",
  "attack": 1950,
  "defense": 2100,
  "level": 6,
  "attribute": "WIND",
  "race": "Winged Beast",
  "images": {
    "artwork_url": "https://images.ygoprodeck.com/images/cards/49858495.jpg",
    "small_url": "https://images.ygoprodeck.com/images/cards_small/49858495.jpg",
    "cropped_url": "https://images.ygoprodeck.com/images/cards_cropped/49858495.jpg"
  }
}
