{
  "id": 52430902,
  "name": "Psychic Jumper",
  "type": "Tuner Monster",
  "description": "Once per turn: You can pay 1000 LP, then target 1 face-up monster your opponent controls and 1 Psychic-Type monster you control, except \"Psychic Jumper\"; switch control of both those targets, and if you do, their battle positions cannot be changed this turn.",
  "attack": 100,
  "defense": 1500,
  "level": 2,
  "attribute": "EARTH",
  "race": "Psychic",
  "images": {
    "artwork_url": "https://images.ygoprodeck.com/images/cards/52430902.jpg",
    "small_url": "https://images.ygoprodeck.com/images/cards_small/52430902.jpg",
    "cropped_url": "https://images.ygoprodeck.com/images/cards_cropped/52430902.jpg"
  }
}
