{
  "id": 40838625,
  "name": "Quaking Mirror Force",
  "type": "Trap Card",
  "description": "When an opponent's monster declares an attack: Change all your opponent's Attack Position monsters to face-down Defense Position. Monsters changed to face-down Defense Position by this effect cannot change their battle positions.",
  "race": "Normal",
  "images": {
    "artwork_url": "https://images.ygoprodeck.com/images/cards/40838625.jpg",
    "small_url": "https://images.ygoprodeck.com/images/cards_small/40838625.jpg",
    "cropped_url": "https://images.ygoprodeck.com/images/cards_cropped/40838625.jpg"
  }
}
