{
  "id": 35334193,
  "name": "S-Force Justify",
  "type": "Link Monster",
  "description": "3 Effect Monsters, including an \"S-Force\" monster\r\nYou cannot Summon/Set monsters to a zone(s) this card points to. (Quick Effect): You can target 1 face-up Effect Monster your opponent controls; negate its effects until the end of this turn, then you can move that opponent's monster to their Monster Zone this card points to. You can only use this effect of \"S-Force Justify\" once per turn. At the start of the Damage Step, if this card attacks: You can banish all monsters this card points to.",
  "attack": 2600,
  "defense": null,
  "level": null,
  "attribute": "LIGHT",
  "race": "Cyberse",
  "images": {
    "artwork_url": "https://images.ygoprodeck.com/images/cards/35334193.jpg",
    "small_url": "https://images.ygoprodeck.com/images/cards_small/35334193.jpg",
    "cropped_url": "https://images.ygoprodeck.com/images/cards_cropped/35334193.jpg"
  }
}
