{
  "id": 45819647,
  "name": "Selene, Queen of the Master Magicians",
  "type": "Link Monster",
  "description": "2+ monsters, including a Spellcaster monster\r\nIf this card is Link Summoned: Place Spell Counters on this card, equal to the number of Spells on the field and in the GYs. While an \"Endymion\" card(s) is on the field, your opponent's monsters cannot target this card for attacks. Once per turn, during the Main Phase (Quick Effect): You can remove 3 Spell Counters from your field; Special Summon 1 Spellcaster monster from your hand or GY in Defense Position, to your zone this card points to.",
  "attack": 1850,
  "defense": null,
  "level": null,
  "attribute": "LIGHT",
  "race": "Spellcaster",
  "images": {
    "artwork_url": "https://images.ygoprodeck.com/images/cards/45819647.jpg",
    "small_url": "https://images.ygoprodeck.com/images/cards_small/45819647.jpg",
    "cropped_url": "https://images.ygoprodeck.com/images/cards_cropped/45819647.jpg"
  }
}
