{
  "id": 6733059,
  "name": "Skull Lair",
  "type": "Trap Card",
  "description": "Remove from play any number of Monster Cards in your Graveyard to destroy 1 face-up monster on the field whose Level is equal to the number of the cards you removed from play.",
  "race": "Continuous",
  "images": {
    "artwork_url": "https://images.ygoprodeck.com/images/cards/6733059.jpg",
    "small_url": "https://images.ygoprodeck.com/images/cards_small/6733059.jpg",
    "cropped_url": "https://images.ygoprodeck.com/images/cards_cropped/6733059.jpg"
  }
}
