{
  "id": 38275183,
  "name": "Spell Shield Type-8",
  "type": "Trap Card",
  "description": "Activate 1 of these effects.\n● When a Spell Card is activated that targets exactly 1 monster on the field: Negate the activation, and if you do, destroy it.\n● When a Spell Card is activated: Send 1 Spell Card from your hand to the Graveyard; negate the activation, and if you do, destroy it.",
  "race": "Counter",
  "images": {
    "artwork_url": "https://images.ygoprodeck.com/images/cards/38275183.jpg",
    "small_url": "https://images.ygoprodeck.com/images/cards_small/38275183.jpg",
    "cropped_url": "https://images.ygoprodeck.com/images/cards_cropped/38275183.jpg"
  }
}
