{
  "id": 96148285,
  "name": "Triggered Summon",
  "type": "Trap Card",
  "description": "Activate only when a monster is Special Summoned to your opponent's side of the field. Each player can Special Summon 1 Level 4 or lower monster from their hand.",
  "race": "Normal",
  "images": {
    "artwork_url": "https://images.ygoprodeck.com/images/cards/96148285.jpg",
    "small_url": "https://images.ygoprodeck.com/images/cards_small/96148285.jpg",
    "cropped_url": "https://images.ygoprodeck.com/images/cards_cropped/96148285.jpg"
  }
}
