{
  "id": 16366810,
  "name": "Yellow Duston",
  "type": "Effect Monster",
  "description": "Cannot be used as a Fusion, Synchro, or Xyz Material for a Summon. While this card is face-up on the field, it cannot be Tributed. When this card on the field is destroyed: The controller targets 1 monster in their Graveyard; shuffle that target into the Deck. You can only control 1 face-up \"Yellow Duston\".",
  "attack": 0,
  "defense": 1000,
  "level": 1,
  "attribute": "EARTH",
  "race": "Fiend",
  "images": {
    "artwork_url": "https://images.ygoprodeck.com/images/cards/16366810.jpg",
    "small_url": "https://images.ygoprodeck.com/images/cards_small/16366810.jpg",
    "cropped_url": "https://images.ygoprodeck.com/images/cards_cropped/16366810.jpg"
  }
}
